textual_forms/__init__.py
textual_forms/buttons.py
textual_forms/fields.py
textual_forms/forms.py
textual_forms/validators.py
textual_forms-0.3.0.dist-info/LICENSE
textual_forms-0.3.0.dist-info/WHEEL
textual_forms-0.3.0.dist-info/METADATA
textual_forms-0.3.0.dist-info/RECORD
